nest/hello.py
nest/init.py
nest/main.py
nest_pip_package-0.1.0.dist-info/METADATA
nest_pip_package-0.1.0.dist-info/WHEEL
nest_pip_package-0.1.0.dist-info/licenses/LICENSE
nest_pip_package-0.1.0.dist-info/RECORD
