Metadata-Version: 2.4
Name: nest-pip-package
Version: 0.1.0
Summary: Example
Author-email: You <you@example.com>
License: Copyright (c) <year> <copyright holders>
License-File: LICENSE
Requires-Python: >=3.8
